{
  "posts": [
    {
      "id": 74611951,
      "title": "Junius",
      "author": "Dock Donnelly",
      "content": "a hic aut"
    },
    {
      "id": 41375273,
      "title": "Britney",
      "author": "Sabryna Orn",
      "content": "porro reprehenderit explicabo"
    },
    {
      "id": 32661736,
      "title": "Alia",
      "author": "Darion Eichmann",
      "content": "velit ut reprehenderit"
    },
    {
      "id": 36597433,
      "title": "Mable",
      "author": "Rod Wiza",
      "content": "dicta doloribus sit"
    },
    {
      "id": 49073813,
      "title": "Ross",
      "author": "Tess Daniel Sr.",
      "content": "fuga repudiandae unde"
    }
  ]
}